ios_build/README.md
ios_build/__init__.py
ios_build/__main__.py
ios_build/build.py
ios_build/cmake.py
ios_build/errors.py
ios_build/interface.py
ios_build/logo.txt
ios_build/parser.py
ios_build/printer.py
ios_build/run.py
ios_build/search.py
ios_build/toolchain.py
ios_build/xcodebuild.py
iosbuild-0.2.0.dist-info/METADATA
iosbuild-0.2.0.dist-info/WHEEL
iosbuild-0.2.0.dist-info/entry_points.txt
iosbuild-0.2.0.dist-info/licenses/LICENSE
iosbuild-0.2.0.dist-info/RECORD
