Metadata-Version: 2.4
Name: iOSBuild
Version: 0.2.0
Summary: A Python script for creating XCFrameworks for CMake projects
Project-URL: Repository, https://github.com/zwill22/iOSBuild
Project-URL: Documentation, https://iosbuild.readthedocs.io/en/latest/
Author-email: Z M Williams <z.m.will@icloud.com>
License: MIT License
License-File: LICENSE
Keywords: Apple,CMake,MacOS,XCFramework,iOS
Classifier: License :: OSI Approved :: MIT License
Classifier: Operating System :: MacOS
Classifier: Programming Language :: Python
Classifier: Programming Language :: Python :: 3
Classifier: Programming Language :: Python :: 3.9
Classifier: Programming Language :: Python :: 3.10
Classifier: Programming Language :: Python :: 3.11
Classifier: Programming Language :: Python :: 3.12
Classifier: Programming Language :: Python :: 3.13
Requires-Python: >=3.9
Requires-Dist: cmake>=3.22
Requires-Dist: requests
Provides-Extra: dev
Requires-Dist: coverage; extra == 'dev'
Requires-Dist: pytest; extra == 'dev'
Requires-Dist: ruff; extra == 'dev'
